README.md
setup.py
ogms/__init__.py
ogms.egg-info/PKG-INFO
ogms.egg-info/SOURCES.txt
ogms.egg-info/dependency_links.txt
ogms.egg-info/requires.txt
ogms.egg-info/top_level.txt
ogms.egg-info/zip-safe
ogms/context/IModelServiceContext.py
ogms/context/ModelServiceContextLite.py
ogms/context/__init__.py
ogms/context/modelTest.py
ogms/context/modeldatahandler.py
ogms/context/modelservicecontext.py
ogms/mdl/AttributeSet.py
ogms/mdl/Behavior.py
ogms/mdl/IAttributeSet.py
ogms/mdl/IBehavior.py
ogms/mdl/IModelClass.py
ogms/mdl/IRuntime.py
ogms/mdl/ModelClass.py
ogms/mdl/Runtime.py
ogms/mdl/__init__.py
ogms/mdl/mdl_test.py
ogms/modelservice/__init__.py
ogms/modelservice/base.py
ogms/modelservice/data.py
ogms/modelservice/geodatacontainerserver.py
ogms/modelservice/geodataexserver.py
ogms/modelservice/geotaskserver.py
ogms/modelservice/modelserivce.py
ogms/modelservice/modelserviceinstance.py
ogms/modelservice/modelservicerecord.py
ogms/modelservice/runninglog.py
ogms/modelservice/server.py
ogms/modelservice/servicecollection.py
ogms/modelservice/utils.py